{
    "metric": "accuracy",
    "generated_at_utc": "2026-04-16T09:46:27.978461+00:00",
    "dataset_sizes": {
        "training": 1884,
        "validation": 513,
        "test": 133
    },
    "execution_order": [
        "null_model",
        "always_zero",
        "always_one",
        "lasso_logistic",
        "logistic_regression",
        "random_forest"
    ],
    "ranking": [
        {
            "model": "lasso_logistic",
            "metric": "accuracy",
            "validation_accuracy": 0.5224171539961013,
            "best_C": 1,
            "selected_variables": 51,
            "test_accuracy": 0.5413533834586466
        },
        {
            "model": "logistic_regression",
            "metric": "accuracy",
            "selected_variables": 51,
            "test_accuracy": 0.5413533834586466
        },
        {
            "model": "always_zero",
            "metric": "accuracy",
            "predicted_class": 0,
            "test_accuracy": 0.5338345864661654
        },
        {
            "model": "random_forest",
            "metric": "accuracy",
            "validation_accuracy": 0.543859649122807,
            "best_params": {
                "n_estimators": 200,
                "max_depth": 3,
                "min_samples_leaf": 10,
                "max_features": "sqrt"
            },
            "selected_variables": 51,
            "test_accuracy": 0.5338345864661654
        },
        {
            "model": "null_model",
            "metric": "accuracy",
            "predicted_class": 1,
            "test_accuracy": 0.46616541353383456
        },
        {
            "model": "always_one",
            "metric": "accuracy",
            "predicted_class": 1,
            "test_accuracy": 0.46616541353383456
        }
    ],
    "best_model": "lasso_logistic",
    "best_accuracy": 0.5413533834586466,
    "tied_best_models": [
        "lasso_logistic",
        "logistic_regression"
    ]
}